README.txt
setup.cfg
setup.py
Products/__init__.py
Products.RoleAwarePortlet.egg-info/PKG-INFO
Products.RoleAwarePortlet.egg-info/SOURCES.txt
Products.RoleAwarePortlet.egg-info/dependency_links.txt
Products.RoleAwarePortlet.egg-info/entry_points.txt
Products.RoleAwarePortlet.egg-info/namespace_packages.txt
Products.RoleAwarePortlet.egg-info/not-zip-safe
Products.RoleAwarePortlet.egg-info/requires.txt
Products.RoleAwarePortlet.egg-info/top_level.txt
Products/RoleAwarePortlet/__init__.py
Products/RoleAwarePortlet/configure.zcml
Products/RoleAwarePortlet/browser/__init__.py
Products/RoleAwarePortlet/browser/configure.zcml
Products/RoleAwarePortlet/browser/image.py
Products/RoleAwarePortlet/browser/portlet.pt
Products/RoleAwarePortlet/browser/portlet.py
Products/RoleAwarePortlet/browser/vocabulary.py
Products/RoleAwarePortlet/i18n/RoleAwarePortlet-de-plone.po
Products/RoleAwarePortlet/i18n/RoleAwarePortlet-fr-plone.po
Products/RoleAwarePortlet/profiles/default/metadata.xml
Products/RoleAwarePortlet/profiles/default/portlets.xml
Products/RoleAwarePortlet/profiles/default/propertiestool.xml
docs/HISTORY.txt