Metadata-Version: 1.0
Name: Products.RoleAwarePortlet
Version: 1.0b3
Summary: Provides a portlet which is visible only for specific roles
Home-page: http://raptus.com
Author: Raptus AG
Author-email: dev@raptus.com
License: GPL
Platform: UNKNOWN
Classifier: Programming Language :: Python
Classifier: Topic :: Software Development :: Libraries :: Python Modules
